{"label": "אמריקן יוניברסיטי", "pin": {"location": {"lat": 38.937055, "lon": -77.086922}}, "url": "https://he.wikipedia.org/wiki/אמריקן_יוניברסיטי", "abstract": "אמריקן יוניברסיטי (באנגלית: American University, AU) היא אוניברסיטה פרטית בוושינגטון די. סי. המצטיינת בעיקר בתחומי לימוד שנועדו להכשרת אנשי ציבור, דיפלומטים ומדינאים כיחסים בינלאומיים, מנהל ציבורי, מדיניות ציבורית ומדע המדינה ותחומים משיקים כתקשורת המונים, כלכלה ומשפטים. האוניברסיטה, שנוסדה בשנת 1893 על ידי הכומר המתודיסטי ג'ון פלטשר הרסט , מורכבת משמונה קולג'ים ובתי ספר: בית הספר לשירות הבינלאומי (SIS), בית הספר לשירות הציבורי (SPA), בית הספר לתקשורת, הקולג' למדעים ואומנויות, בית הספר ללימודים מתקדמים, בית הספר למנהל עסקים ולכלכלה ע\"ש רוברט קוגוד, בית ספר לחינוך וקולג' וושינגט"}