{"label": "אמסטרדם המרכזית", "coordinates": {"lat": 52.369985, "lon": 4.898014}, "url": "https://he.wikipedia.org/wiki/אמסטרדם_המרכזית", "abstract": "עונת 1953/1954 היא העונה השמינית של ליגת ה-NBA. העונה הסתיימה זכייתה השלישית ברציפות והחמישית בסך הכול של מיניאפוליס לייקרס בתואר האליפות, לאחר שגברה על סירקיוז נשיונלס בסדרת הגמר בתוצאה 4-3. הסנטר ג'ורג' מייקן הוביל את קלעי האלופה בסדרת הגמר, כשקלע 18.1 נקודות בממוצע למשחק. בתחילת העונה התפרקה קבוצת אינדיאנפוליס אולימפיאנס, מה שצמצם את מספר קבוצות הליגה לתשע בלבד."}