{"label": "ארזורום (נפה)", "coordinates": {"lat": 40.06305556, "lon": 41.56694444}, "url": "https://he.wikipedia.org/wiki/ארזורום_(נפה)", "abstract": "חבובוטף (באנגלית: Muppet Babies) היא סדרת אנימציה בת 107 פרקים שהופקה לטלוויזיה בין השנים 1984‏-1991 ב-CBS. בישראל שודרה הסדרה בערוץ הראשון בין השנים 1988‏-1989 וכיום משודרת בערוץ ג'וניור ב-yes. החבובוטף הופיעו לראשונה בסרט \"החבובות כובשות את מנהטן\". בשנת 2018 נוצרה גרסה מחודשת לסדרה בשם \"חבובוטף\" באנימציה ממוחשבת ותלת ממדית. האנימציה של הסדרה המחודשת נעשתה בישראל בסטודיו SnowBall, והיא משודרת בערוץ דיסני ג'וניור, כשאת דמויותיהם של סקוטר וסקיטר מחליפה דמות מקורית בשם \"סאמר פינגווין\". הסדרה משודרת בדיבוב לעברית בערוץ דיסני ובדיסני ג'וניור ב-2019."}