{"label": "דיסניקווסט", "coordinates": {"lat": 28.3703, "lon": -81.5221}, "url": "https://he.wikipedia.org/wiki/דיסניקווסט", "abstract": "אנטוניו ז'וזה דה סילווה (בפורטוגזית: António José da Silva Coutinho) (8 במאי 1705 ריו דה ז'ניירו - 18 באוקטובר 1739, ליסבון) היה מחזאי פורטוגזי - ברזילאי, ממוצא יהודי, שנחשב ליוצר התיאטרון הפורטוגלי הקומי המודרני. כינויו היה \"היהודי\" ומן המהדורה הראשונה של ספרו, \"התיאטרון הקומי הפורטוגלי או קובץ האופרות והיצירות הפורטוגליות\" הושמט שמו. במקום השם נכתב ***."}