{"label": "המתחם הדתי בקלוואריה זבז'ידובסקה", "coordinates": {"lat": 49.86027778, "lon": 19.67055556}, "url": "https://he.wikipedia.org/wiki/המתחם_הדתי_בקלוואריה_זבז'ידובסקה", "abstract": "דיירי קווין (באנגלית: Dairy Queen או בקיצור DQ) היא רשת של גלידריות וחנויות לממכר מזון מהיר. החנות הראשונה ברשת נוסדה בשנת 1938 על ידי ג'ון מק'קאלוו, ומאז 1940 היא הרחיבה את פעילותה בארצות הברית ובמדינות אחרות באמצעות שיטת הזכיינות. הזכיינית הגדולה ביותר של החברה היא Texas Dairy Queen Operating Council המפעילה את מרבית סניפי הרשת בטקסס. החברה המחזיקה בזכויות על המותג היא דיירי קווין אינטרנשיונל, ובארצות הברית היא פועלת באמצעות חברת הבת אמריקן דיירי קווין. בסוף 2006 דיווחה דיירי קווין כי ברשת יותר מ-5,700 סניפים ביותר מתריסר מדינות (מהם 4,600 בארצות הברית). נכון לאוקטובר 2016 אין לרשת סניפים בישרא"}