{"label": "חיספין", "coordinates": {"lat": 32.84552489, "lon": 35.79375629}, "url": "https://he.wikipedia.org/wiki/חיספין", "abstract": "לונדיניום היא עיר עתיקה עליה נבנתה לימים בירת הממלכה המאוחדת – לונדון. העיר נוסדה לאחר הכיבוש הרומי של האי בריטניה בשנת 43 על ידי הקיסר הרומאי קלאודיוס. קלאודיוס שלח ארבעה לגיונות על מנת לכבוש את בריטניה לאחר שקיבל פניה מאחד מראשי השבטים הקלטים היריבים שהתגוררו באי. בריטניה הייתה מטרה אטרקטיבית לרומאים בשל עושרה במחצבים ובעבדים, וכן מאחר שהאי שימש גם כמקלט למורדים מפרובינקיות אחרות. קלאודיוס עצמו ביקר באי לאחר השלמת השלב הראשון של הלחימה, והביא עמו תגבורת המלווה בפילים."}