{"label": "מיידאן-י אמאם", "coordinates": {"lat": 32.65722222, "lon": 51.6775}, "url": "https://he.wikipedia.org/wiki/מיידאן-י_אמאם", "abstract": "מחלקת השימור של ניו זילנד (באנגלית: Department of Conservation; במאורית - Te Papa Atawhai) הידועה גם בראשי התיבות DOC היא הגוף האחראי על שמירת הטבע והאתרים ההיסטוריים בניו זילנד. מחלקת השימור היא גוף ציבורי הכפוף לשר השימור (Minister of Conservation) ניק סמית'(Hon Dr Nick Smith) ובתחום אחריותה נמצאות שמורות טבע ופארקים לאומיים המכסים כשליש משטחה של ניו זילנד."}