{"label": "מרום נווה", "coordinates": {"lat": 32.07175, "lon": 34.83066667}, "url": "https://he.wikipedia.org/wiki/מרום_נווה", "abstract": "גברילו פרינציפ (בסרבית: Гаврило Принцип; 25 ביולי 1894 - 28 באפריל 1918) היה תושב סרבי שהיה חבר בקבוצת היד השחורה ובוסניה הצעירה. התנקש בחייהם של יורש העצר האוסטרו-הונגרי הארכידוכס פרנץ פרדיננד ורעייתו בסרייבו ב-28 ביוני 1914. ההתנקשות, הידועה בשם \"הרצח בסרייבו\", נחשבת על ידי רבים כגורם הישיר לפעולת האימפריה האוסטרו-הונגרית נגד ממלכת סרביה, שהובילה לפרוץ מלחמת העולם הראשונה. עם זאת, רבים אחרים סבורים כי ההתנקשות היוותה רק תירוץ לפעולה אוסטרו-הונגרית נגד סרביה, שתוכננה ממילא עוד קודם לכן."}