{"label": "פארק אלרטון (אילינוי)", "coordinates": {"lat": 39.998, "lon": -88.65}, "url": "https://he.wikipedia.org/wiki/פארק_אלרטון_(אילינוי)", "abstract": "ואנג בי (בסינית: 王弼; 226-249) או בשמו הספרותי פוּ-סֶה, היה פילוסוף סיני שהשתייך לזרם הניאוטאואיזם בפילוסופיה הסינית. וונג בי הוא אחד הפילוסופים הסינים החשובים והמוכרים בסין ובמערב משום שבסין החידושים הפילוסופים בפירושים שלו ל\"ספר הדרך והסגולה\" ו\"האי צ'ינג\" התאימו הן לקונפוציאנים והן לטאואיסטים ואפילו לבודהיסטים שבאו אחריו, ובמערב משום שהגרסה שבה הוא השתמש של ספר הדרך והסגולה  היא הגרסה המפורשת הכי נפוצה."}