{"label": "פלימות' (מונטסראט)", "coordinates": {"lat": 16.70641667, "lon": -62.21583889}, "url": "https://he.wikipedia.org/wiki/פלימות'_(מונטסראט)", "abstract": "תיירות בישראל היא מכלול החוויות אשר זמינות בישראל וכוללת את תיירות הפנים ואת המבקרים בישראל ממדינות אחרות. ערי התיירות המובילות בישראל הן ירושלים, תל אביב, אילת וטבריה, והאתרים המובילים מחוץ לערים הם ים המלח ומצדה. יתרונותיה התיירותיים של מדינת ישראל כוללים תשתית תיירות ענפה, אקלים נוח ומגוון, וריכוז גבוה של אתרים היסטוריים, דתיים וארכאולוגיים, כמו גם אתרי טבע ותרבות רבים, בקרבה גבוהה יחסית."}