{"label": "צ'יזרינג", "pin": {"location": {"lat": 50.52535556, "lon": -4.45929444}}, "url": "https://he.wikipedia.org/wiki/צ'יזרינג", "abstract": "צ'יזרינג (באנגלית: Cheesewring, בקורנית: Keuswask) הוא טור גרניט בקורנוול בבריטניה, השוכן באגף המזרחי של בודמין מור (Bodmin Moor) על גבעת סטואו (Stowe's Hill) בקהילה של לינקונהורן (Linkinhorne), כקילומטר וחצי מהכפר מיניונס (Minions) וכ-6 קילומטרים צפונית לליסקרד (Liskeard). הצ'יזרינג הוא תצורה גאולוגית טבעית, מחשוף סלע של לוחות גרניט שנוצר עקב סחיפה."}