{"label": "קהילת תאומי האלון", "pin": {"location": {"lat": 37.93306944, "lon": -77.99414167}}, "url": "https://he.wikipedia.org/wiki/קהילת_תאומי_האלון", "abstract": "קהילת תאומי האלון (באנגלית: Twin Oaks Community) הוא כפר אקולוגי וקהילה רצונית בה חיים כמאה אנשים, בשטח של 450 אקרים בו. הקהילה היא חלק מהתאחדות הקהילות השוויונית. מאז היווסדה ב-1967, קהילת תאומי האלון היא בין הקהילות הרצוניות החילוניות ארוכות החיים בצפון אמריקה. הערכים הבסיסים של הקהילה הם שיתוף, שוויון, אי-אלימות, קיימות וחלוקת הכנסה."}