{"label": "קורוסטן", "coordinates": {"lat": 50.95, "lon": 28.63333333}, "url": "https://he.wikipedia.org/wiki/קורוסטן", "abstract": "מתחם דוּלוּת (באנגלית : Duluth Complex), מתחם מפרץ ביוור (Beaver Bay Complex) המשויך אליו (ושלעיתים קרובות מתייחסים אליו כחלק ממתחם דולות), והמתחם הגעשי נורת שור (North Shore Volcanic Group) הקשור אליהם הם תצורות סלעים הבונות את מרבית תשתית סלע האם של צפון מזרח מדינת מינסוטה. מתחם דולות ומתחם מפרץ ביוור הם מחדרים שכבתיים שנוצרו בעת היווצרות אזור ההעתקים המרכז-יבשתי (Midcontinent Rift System) של אמריקה הצפונית."}